netcup_webservice/__init__.py
netcup_webservice/netcup.py
netcup_webservice-0.1.7.dist-info/LICENSE
netcup_webservice-0.1.7.dist-info/METADATA
netcup_webservice-0.1.7.dist-info/WHEEL
netcup_webservice-0.1.7.dist-info/top_level.txt
netcup_webservice-0.1.7.dist-info/RECORD
