Metadata-Version: 2.1
Name: netcup-webservice
Version: 0.1.7
Summary: Unofficial Python client for Netcup Webservice API
Home-page: https://github.com/mihneamanolache/netcup-webservice
Author: Mihnea-Octavian Manolache
Author-email: me@mihnea.dev
License: MIT
Classifier: Programming Language :: Python :: 3
Classifier: License :: OSI Approved :: MIT License
Classifier: Operating System :: OS Independent
Requires-Python: >=3.6
License-File: LICENSE
Requires-Dist: zeep
